SCINApy/__init__.py
SCINApy/core.py
SCINApy/interface.py
SCINApy/utils.py
SCINApy/visual.py
scinapy-0.1.2.dist-info/licenses/LICENSE
scinapy-0.1.2.dist-info/METADATA
scinapy-0.1.2.dist-info/WHEEL
scinapy-0.1.2.dist-info/top_level.txt
scinapy-0.1.2.dist-info/RECORD
